MANIFEST.in
README.md
setup.py
blog/__init__.py
blog/__version__.py
blog/blog.py
blog/lib/degate_mac.so
jaki_sdk_python.egg-info/PKG-INFO
jaki_sdk_python.egg-info/SOURCES.txt
jaki_sdk_python.egg-info/dependency_links.txt
jaki_sdk_python.egg-info/requires.txt
jaki_sdk_python.egg-info/top_level.txt
requirements/requirement.txt