Metadata-Version: 2.1
Name: jaki-sdk-python
Version: 1.4.0
Summary: This is a lightweight library that works as a connector to Jaki public API.
Home-page: https://github.com/kobesjava/python-sdk.git
Author: Jaki
License: MIT
Keywords: Jaki,Public API
Platform: UNKNOWN
Requires-Python: >=3.6
